emb_ser_protocol/__init__.py
emb_ser_protocol/protocol.py
emb_ser_protocol/version.py
emb_ser_protocol-1.1.23.dist-info/METADATA
emb_ser_protocol-1.1.23.dist-info/WHEEL
emb_ser_protocol-1.1.23.dist-info/licenses/LICENSE
emb_ser_protocol-1.1.23.dist-info/RECORD
