Metadata-Version: 2.1
Name: emb_ser_protocol
Version: 1.1.23
Summary: A simple serial protocol for communicating with embedded devices.
Project-URL: Homepage, https://github.com/pypa/emb_ser_protocol
Project-URL: Bug Tracker, https://github.com/pypa/emb_ser_protocol/issues
Author-email: Warren Woolsey <budgettsfrog@protonmail.com>
License-File: LICENSE
Classifier: License :: OSI Approved :: MIT License
Classifier: Operating System :: OS Independent
Classifier: Programming Language :: Python :: 3
Requires-Python: >=3.7
